agodashi/__init__.py
agodashi/app.py
agodashi/const.py
agodashi/controller.py
agodashi/cwl.py
agodashi/type.py
agodashi/util.py
agodashi-1.0.1.dist-info/LICENSE
agodashi-1.0.1.dist-info/METADATA
agodashi-1.0.1.dist-info/WHEEL
agodashi-1.0.1.dist-info/entry_points.txt
agodashi-1.0.1.dist-info/top_level.txt
agodashi-1.0.1.dist-info/RECORD
