Metadata-Version: 2.1
Name: agodashi
Version: 1.0.1
Summary: An API server for parsing workflows written in workflow languages
Home-page: https://github.com/suecharo/agodashi
Author: suecharo
Author-email: suehiro619@gmail.com
License: Apache2.0
Platform: any
Classifier: Programming Language :: Python
Requires-Python: >=3.6
Requires-Dist: cwltool
Requires-Dist: flake8
Requires-Dist: Flask
Requires-Dist: isort
Requires-Dist: jsonschema
Requires-Dist: mypy
Requires-Dist: pytest
Requires-Dist: PyYAML
Requires-Dist: requests
